OpenATS/__init__.py
OpenATS/version.py
OpenATS/scripts/__init__.py
OpenATS/scripts/command.py
OpenATS/scripts/version.py
OpenATS-0.1.dev3.dist-info/DESCRIPTION.rst
OpenATS-0.1.dev3.dist-info/METADATA
OpenATS-0.1.dev3.dist-info/RECORD
OpenATS-0.1.dev3.dist-info/WHEEL
OpenATS-0.1.dev3.dist-info/entry_points.txt
OpenATS-0.1.dev3.dist-info/metadata.json
OpenATS-0.1.dev3.dist-info/top_level.txt
